pybling/__init__.py
pybling/contacts.py
pybling/notas.py
pybling/products.py
pybling-0.0.9.dist-info/LICENSE
pybling-0.0.9.dist-info/METADATA
pybling-0.0.9.dist-info/WHEEL
pybling-0.0.9.dist-info/top_level.txt
pybling-0.0.9.dist-info/RECORD
