Metadata-Version: 2.1
Name: pybling
Version: 0.0.9
Summary: Integração com API do Bling usando Python
Home-page: https://github.com/tiagocordeiro/pybling.git
Author: Tiago Cordeiro
Author-email: tiago@mulhergorila.com
License: MIT
Platform: UNKNOWN
Classifier: Development Status :: 4 - Beta
Classifier: Environment :: Web Environment
Classifier: Intended Audience :: Developers
Classifier: License :: OSI Approved :: MIT License
Classifier: Operating System :: OS Independent
Classifier: Programming Language :: Python :: 3
Classifier: Framework :: Paste
Requires-Dist: python-dotenv (>=0.10.1)
Requires-Dist: requests (>=2.21.0)
